CHANGES.txt
README.txt
setup.py
src/cloudooo/__init__.py
src/cloudooo.handler.ffmpeg.egg-info/PKG-INFO
src/cloudooo.handler.ffmpeg.egg-info/SOURCES.txt
src/cloudooo.handler.ffmpeg.egg-info/dependency_links.txt
src/cloudooo.handler.ffmpeg.egg-info/entry_points.txt
src/cloudooo.handler.ffmpeg.egg-info/namespace_packages.txt
src/cloudooo.handler.ffmpeg.egg-info/requires.txt
src/cloudooo.handler.ffmpeg.egg-info/top_level.txt
src/cloudooo/handler/__init__.py
src/cloudooo/handler/ffmpeg/__init__.py
src/cloudooo/handler/ffmpeg/handler.py
src/cloudooo/handler/ffmpeg/tests/__init__.py
src/cloudooo/handler/ffmpeg/tests/runFFMPEGHandlerUnitTest.py
src/cloudooo/handler/ffmpeg/tests/testAllVideoSupportedFormat.py
src/cloudooo/handler/ffmpeg/tests/testFFMPEGHandler.py
src/cloudooo/handler/ffmpeg/tests/testInterface.py
src/cloudooo/handler/ffmpeg/tests/testServer.py
src/cloudooo/handler/ffmpeg/tests/data/test.ogv