Metadata-Version: 1.0
Name: cloudooo.handler.ffmpeg
Version: 0.1
Summary: Python Package to handle Videos
Home-page: UNKNOWN
Author: Gabriel M. Monnerat
Author-email: gabriel@tiolive.com
License: GPL
Keywords: python ffmpeg
Platform: UNKNOWN
Classifier: Programming Language :: Python :: 2.6
Classifier: Natural Language :: English
